CHANGES.rst
LICENSE
MANIFEST.in
README.rst
dev-requirements.txt
setup.py
Flask_Split_JS.egg-info/PKG-INFO
Flask_Split_JS.egg-info/SOURCES.txt
Flask_Split_JS.egg-info/dependency_links.txt
Flask_Split_JS.egg-info/not-zip-safe
Flask_Split_JS.egg-info/requires.txt
Flask_Split_JS.egg-info/top_level.txt
bin/uglify
flask_split_js/__init__.py
flask_split_js/static/js/flask-split.js
flask_split_js/static/js/flask-split.min.js
tests/__init__.py
tests/js/test_ab_test.js
tests/js/test_finished.js
tests/js/utils.js
tests/python/__init__.py
tests/python/test_views.py