Metadata-Version: 1.0
Name: Flask-Split-JS
Version: 0.1.0
Summary: A JavaScript library for Flask-Split.
Home-page: http://github.com/FelixLoether/flask-split-js
Author: Oskari Hiltunen
Author-email: flask-split-js@loethr.net
License: MIT
Platform: any
Classifier: Development Status :: 4 - Beta
Classifier: Environment :: Web Environment
Classifier: Framework :: Flask
Classifier: Intended Audience :: Developers
Classifier: License :: OSI Approved :: MIT License
Classifier: Operating System :: OS Independent
Classifier: Programming Language :: Python
Classifier: Topic :: Internet :: WWW/HTTP :: Dynamic Content
Classifier: Topic :: Software Development :: Libraries :: Python Modules
